collider/__init__.py
collider/collider.cpython-311-i386-linux-gnu.so
collider_py-0.0.1.dist-info/METADATA
collider_py-0.0.1.dist-info/WHEEL
collider_py-0.0.1.dist-info/licenses/LICENSE
collider_py-0.0.1.dist-info/RECORD
