Metadata-Version: 2.4
Name: collider_py
Version: 0.0.1
Classifier: Programming Language :: Rust
Classifier: Programming Language :: Python :: Implementation :: CPython
Classifier: Programming Language :: Python :: Implementation :: PyPy
License-File: LICENSE
Summary: An experimental collision-detection library.
Home-Page: https://github.com/agroudiev/collider
Author-email: Antoine Groudiev <antoine.groudiev@ens.psl.eu>
Requires-Python: >=3.8
